speaknow.py
speaknow_serve.py
speaknow_ai_realtime_text_to_speech/__init__.py
speaknow_ai_realtime_text_to_speech/__version__.py
speaknow_ai_realtime_text_to_speech/app_css.py
speaknow_ai_realtime_text_to_speech/audio_util.py
speaknow_ai_realtime_text_to_speech/config.py
speaknow_ai_realtime_text_to_speech/config_css.py
speaknow_ai_realtime_text_to_speech/directories.py
speaknow_ai_realtime_text_to_speech/utils.py
speaknow_ai_realtime_text_to_speech/widgets.py
speaknow_ai_realtime_text_to_speech/ai_services/__init__.py
speaknow_ai_realtime_text_to_speech/ai_services/base.py
speaknow_ai_realtime_text_to_speech/ai_services/google_gemini_flash_audio.py
speaknow_ai_realtime_text_to_speech/ai_services/openai_gpt_realtime.py
speaknow_ai_realtime_text_to_speech/ai_services/prices.py
speaknow_ai_realtime_text_to_speech/ai_services/xai_grok_voice.py
speaknow_ai_realtime_text_to_speech/conf/logging.conf
speaknow_gui-0.2.1.dist-info/licenses/LICENSE
speaknow_gui-0.2.1.dist-info/METADATA
speaknow_gui-0.2.1.dist-info/WHEEL
speaknow_gui-0.2.1.dist-info/entry_points.txt
speaknow_gui-0.2.1.dist-info/top_level.txt
speaknow_gui-0.2.1.dist-info/RECORD
