Metadata-Version: 2.4
Name: speaknow-gui
Version: 0.2.1
Summary: Realtime AI Voice Interface using OpenAI Realtime API
Author-email: Paul Martin <paulmartin4work@protonmail.com>
Requires-Python: >=3.11
License-File: LICENSE
Requires-Dist: openai[realtime]
Requires-Dist: sounddevice
Requires-Dist: audioop-lts; python_version >= "3.13"
Requires-Dist: numpy
Requires-Dist: pydub
Requires-Dist: textual
Requires-Dist: textual-dev
Requires-Dist: textual_serve
Requires-Dist: PyYAML
Requires-Dist: gpt-token-tracker
Dynamic: license-file
